mlgw_bns/__init__.py
mlgw_bns/data/ET_psd.txt
mlgw_bns/data/best_trials.pkl
mlgw_bns/data/default.yaml
mlgw_bns/data/default_arrays.h5
mlgw_bns/data/default_nn.pkl
mlgw_bns/data/fast.yaml
mlgw_bns/data/fast_arrays.h5
mlgw_bns/data/fast_nn.pkl
mlgw_bns/data_management.py
mlgw_bns/dataset_generation.py
mlgw_bns/downsampling_interpolation.py
mlgw_bns/fixed_dataset_training.py
mlgw_bns/frequency_of_merger.py
mlgw_bns/hyperparameter_optimization.py
mlgw_bns/model.py
mlgw_bns/model_validation.py
mlgw_bns/multibanding.py
mlgw_bns/neural_network.py
mlgw_bns/principal_component_analysis.py
mlgw_bns/resample_residuals.py
mlgw_bns/taylorf2.py
mlgw_bns-0.12.1.dist-info/LICENSE
mlgw_bns-0.12.1.dist-info/WHEEL
mlgw_bns-0.12.1.dist-info/METADATA
mlgw_bns-0.12.1.dist-info/RECORD
