Metadata-Version: 2.1
Name: mlgw-bns
Version: 0.12.1
Summary: Accelerating gravitational wave template generation with machine learning.
Home-page: https://github.com/jacopok/mlgw_bns
License: GNU GPL3
Keywords: python,gravitational-waves,scientific
Author: Jacopo Tissino
Author-email: jacopo@tissino.it
Requires-Python: >=3.8,<3.11
Classifier: License :: Other/Proprietary License
Classifier: Programming Language :: Python :: 3
Classifier: Programming Language :: Python :: 3.8
Classifier: Programming Language :: Python :: 3.9
Classifier: Programming Language :: Python :: 3.10
Provides-Extra: docs
Requires-Dist: MarkupSafe (==2.0.1); extra == "docs"
Requires-Dist: PyYAML (>=6.0,<7.0)
Requires-Dist: Sphinx (>=4.3.1,<5.0.0); extra == "docs"
Requires-Dist: dacite (>=1.6.0,<2.0.0)
Requires-Dist: h5py (>=3.6.0,<4.0.0)
Requires-Dist: joblib (==1.2.0)
Requires-Dist: myst-parser (>=0.15.2,<0.16.0); extra == "docs"
Requires-Dist: numba (>=0.56.2)
Requires-Dist: numpy (>=1.18,<1.24)
Requires-Dist: optuna (>=2.10.0,<3.0.0)
Requires-Dist: plotly (>=5.5.0,<6.0.0)
Requires-Dist: readthedocs-sphinx-search (>=0.1.1,<0.2.0); extra == "docs"
Requires-Dist: scikit-learn (==1.1.2)
Requires-Dist: sortedcontainers (>=2.4.0,<3.0.0)
Requires-Dist: sphinx-autodoc-defaultargs (>=0.1.2,<0.2.0); extra == "docs"
Requires-Dist: sphinx-rtd-theme (>=1.0.0,<2.0.0); extra == "docs"
Requires-Dist: sphinxcontrib-bibtex (>=2.4.2,<3.0.0); extra == "docs"
Requires-Dist: toml (>=0.10.2,<0.11.0)
Requires-Dist: tqdm (>=4.62.3,<5.0.0)
Requires-Dist: types-PyYAML (>=6.0.11,<7.0.0)
Requires-Dist: types-setuptools (>=57.4.7,<58.0.0)
Project-URL: Repository, https://github.com/jacopok/mlgw_bns
